<annotation>
	<folder>R</folder>
	<filename>R_1367.jpg</filename>
	<path>C:\Users\1Key\Desktop\PET\R\R_1367.jpg</path>
	<source>
		<database>Unknown</database>
	</source>
	<size>
		<width>201</width>
		<height>251</height>
		<depth>1</depth>
	</size>
	<segmented>0</segmented>
	<object>
		<name>available</name>
		<pose>Unspecified</pose>
		<truncated>0</truncated>
		<difficult>0</difficult>
		<bndbox>
			<xmin>72</xmin>
			<ymin>47</ymin>
			<xmax>129</xmax>
			<ymax>205</ymax>
		</bndbox>
	</object>
</annotation>
